Metadata-Version: 2.1
Name: example_package_lewish1998
Version: 0.0.1
Summary: Hello, World!
Author: lewis halstead
Author-email: 
Classifier: Development Status :: 1 - Planning
Classifier: Intended Audience :: Developers
Classifier: Programming Language :: Python :: 3
Classifier: Operating System :: Unix
Classifier: Operating System :: MacOS :: MacOS X
Classifier: Operating System :: Microsoft :: Windows
License-File: LICENSE
